arcane/flask/__init__.py
arcane/flask/authentication.py
arcane/flask/exception_decorator.py
arcane/flask/http_response.py
arcane/flask/log.py
arcane/flask/services.py
arcane/flask/tracking.py
arcane/flask/types.py
arcane_flask-2.2.2.dist-info/METADATA
arcane_flask-2.2.2.dist-info/WHEEL
arcane_flask-2.2.2.dist-info/RECORD
